LICENSE
MANIFEST.in
README.rst
setup.py
django_macaddress_ng.egg-info/PKG-INFO
django_macaddress_ng.egg-info/SOURCES.txt
django_macaddress_ng.egg-info/dependency_links.txt
django_macaddress_ng.egg-info/requires.txt
django_macaddress_ng.egg-info/top_level.txt
macaddress/__init__.py
macaddress/fields.py
macaddress/formfields.py
macaddress/models.py