Metadata-Version: 1.1
Name: django-macaddress-ng
Version: 1.1.0
Summary: MAC address model and form fields for Django apps.
Home-page: http://github.com/kra3/django-macaddress
Author: Arun K. R.
Author-email: the1.arun@gmail.com
License: BSD
Platform: UNKNOWN
Classifier: Development Status :: 5 - Production/Stable
Classifier: Framework :: Django
Classifier: Intended Audience :: Developers
Classifier: License :: OSI Approved :: BSD License
Classifier: Operating System :: OS Independent
Classifier: Programming Language :: Python
Classifier: Topic :: Internet :: WWW/HTTP
